pyshowdown/__init__.py
pyshowdown/client.py
pyshowdown/connection.py
pyshowdown/message.py
pyshowdown/py.typed
pyshowdown/room.py
pyshowdown/user.py
pyshowdown/utils.py
pyshowdown/plugins/__init__.py
pyshowdown/plugins/challstr.py
pyshowdown/plugins/deinit.py
pyshowdown/plugins/init.py
pyshowdown/plugins/plugin.py
pyshowdown/plugins/title.py
pyshowdown/plugins/users.py
pyshowdown-0.3.1.dist-info/licenses/LICENSE
pyshowdown-0.3.1.dist-info/METADATA
pyshowdown-0.3.1.dist-info/WHEEL
pyshowdown-0.3.1.dist-info/top_level.txt
pyshowdown-0.3.1.dist-info/RECORD
