Metadata-Version: 2.4
Name: pyshowdown
Version: 0.3.1
Summary: A client library for the Pokémon Showdown! battle simulator.
Author-email: Scott Maxwell <scott@scotteh.me>
License-Expression: MIT
Project-URL: Homepage, https://github.com/ScottehMax/pyshowdown
Project-URL: Bug Tracker, https://github.com/ScottehMax/pyshowdown/issues
Classifier: Programming Language :: Python :: 3
Classifier: Operating System :: OS Independent
Requires-Python: >=3.9
License-File: LICENSE
Requires-Dist: aiofiles>=0.8.0
Requires-Dist: aiohttp>=3.8.6
Dynamic: license-file
